connectit/__init__.py
connectit/__main__.py
connectit/datasets.py
connectit/dht.py
connectit/hf.py
connectit/model.py
connectit/nat.py
connectit/node.py
connectit/p2p.py
connectit/p2p_runtime.py
connectit/pieces.py
connectit/protocol.py
connectit/utils.py
connectit-0.1.0.dist-info/licenses/LICENSE
connectit-0.1.0.dist-info/METADATA
connectit-0.1.0.dist-info/WHEEL
connectit-0.1.0.dist-info/entry_points.txt
connectit-0.1.0.dist-info/top_level.txt
connectit-0.1.0.dist-info/RECORD
