Metadata-Version: 2.4
Name: connectit
Version: 0.1.0
Summary: Decentralized P2P network for AI model hosting and inference
Author-email: ConnectIT Team <loaiabdalslam@gmail.com>
License: ConnectIT Custom License
Keywords: p2p,ai,machine-learning,distributed,inference,transformers
Classifier: Development Status :: 3 - Alpha
Classifier: Intended Audience :: Developers
Classifier: Intended Audience :: Science/Research
Classifier: Topic :: Scientific/Engineering :: Artificial Intelligence
Classifier: Topic :: System :: Distributed Computing
Classifier: Programming Language :: Python :: 3
Classifier: Programming Language :: Python :: 3.9
Classifier: Programming Language :: Python :: 3.10
Classifier: Programming Language :: Python :: 3.11
Classifier: Programming Language :: Python :: 3.12
Requires-Python: >=3.9
License-File: LICENSE
Requires-Dist: typer>=0.12
Requires-Dist: rich>=13.7
Requires-Dist: websockets>=12.0
Requires-Dist: psutil>=5.9
Requires-Dist: numpy>=1.24
Provides-Extra: hf
Requires-Dist: transformers>=4.40; extra == "hf"
Requires-Dist: datasets>=2.17; extra == "hf"
Provides-Extra: onnx
Requires-Dist: onnx>=1.14; extra == "onnx"
Requires-Dist: onnxruntime>=1.17; extra == "onnx"
Provides-Extra: torch
Requires-Dist: torch>=2.1; (platform_system != "Windows" or platform_machine != "ARM64") and extra == "torch"
Provides-Extra: dht
Requires-Dist: kademlia>=2.2.2; extra == "dht"
Provides-Extra: nat
Requires-Dist: miniupnpc>=2.2.5; extra == "nat"
Requires-Dist: aiortc>=1.9.0; extra == "nat"
Provides-Extra: all
Requires-Dist: transformers>=4.40; extra == "all"
Requires-Dist: datasets>=2.17; extra == "all"
Requires-Dist: onnx>=1.14; extra == "all"
Requires-Dist: onnxruntime>=1.17; extra == "all"
Requires-Dist: torch>=2.1; (platform_system != "Windows" or platform_machine != "ARM64") and extra == "all"
Requires-Dist: kademlia>=2.2.2; extra == "all"
Requires-Dist: miniupnpc>=2.2.5; extra == "all"
Requires-Dist: aiortc>=1.9.0; extra == "all"
Dynamic: license-file
